MANIFEST.in
README
requirements.txt
setup.py
test_requirements.txt
asyncio_hn/__init__.py
asyncio_hn/hn.py
asyncio_hn.egg-info/PKG-INFO
asyncio_hn.egg-info/SOURCES.txt
asyncio_hn.egg-info/dependency_links.txt
asyncio_hn.egg-info/not-zip-safe
asyncio_hn.egg-info/requires.txt
asyncio_hn.egg-info/top_level.txt