Metadata-Version: 1.1
Name: asyncio-hn
Version: 0.2.0
Summary:  Simple asyncio wrapper to download hackernews
Home-page: https://github.com/itielshwartz/asyncio-hn
Author: Itiel Shwartz
Author-email: itiel@etlsh.com
License: MIT license
Keywords: asyncio,aiohttp,hackernews
Platform: UNKNOWN
Classifier: Intended Audience :: Developers
Classifier: License :: OSI Approved :: MIT License
Classifier: Natural Language :: English
Classifier: Programming Language :: Python :: 3.6
